paymobpy
