Metadata-Version: 2.1
Name: paymobpy
Version: 1.0.3
Summary: A client library for paymob API
Home-page: https://github.com/LeOndaz/paymobpy
Author: LeOndaz
Author-email: ahmeddark369@gmail.com
